{
    "dia1": [

        {
            "dia": "13",
            "hora": "03:00 p.m",
            "descripcion": "Encuentro en el parque de las palmas chiminangos",
            "lugar": "tarima principal"
        },
        {
            "dia": "13",
            "hora": "04:00 p.m",
            "descripcion": "Salida y recorrido del carnaval Sancocho Fest",
            "lugar": "tarima junior"
        },
        {
            "dia": "13",
            "hora": "03:00 p.m",
            "descripcion": "Llegada del carnaval obra de teatro 'Gallinas ciegas' Gestos Teatro (Tuluá)",
            "lugar": "Tulua"
        },
        {
            "dia": "13",
            "hora": "03:00 p.m",
            "descripcion": "Presentación cirko pirata (Cali)",
            "lugar": "tarima principal"
        },
        {
            "dia": "13",
            "hora": "08:20 p.m",
            "descripcion": "Don Champignon Concierto Monareta Latin (Tuluá)",
            "lugar": "tarima principal"
        }
    ],

    "dia2": [

        {
            "dia": "14",
            "lugar": "tarima principal",
            "hora": "04:00 pm",
            "descripcion": "Banda de Bugalagrande"
        },
        {
            "dia": "14",
            "lugar": "tarima Junior",
            "hora": "04:40 pm",
            "descripcion": "Jotadufourd Guitarrista argentino"
        },
        {
            "dia": "14",
            "lugar": "tarima Principal",
            "hora": "06:40 pm",
            "descripcion": "Ryan Tennis and the clubhouse Band"
        },
        {
            "dia": "14",
            "lugar": "tarima Principal",
            "hora": "76:40 pm",
            "descripcion": "De tierra caliente"
        }
    ]
}
